opensearchpy/__init__.py
opensearchpy/_version.py
opensearchpy/compat.py
opensearchpy/connection_pool.py
opensearchpy/exceptions.py
opensearchpy/py.typed
opensearchpy/serializer.py
opensearchpy/transport.py
opensearchpy/_async/__init__.py
opensearchpy/_async/_extra_imports.py
opensearchpy/_async/compat.py
opensearchpy/_async/http_aiohttp.py
opensearchpy/_async/transport.py
opensearchpy/_async/client/__init__.py
opensearchpy/_async/client/_patch.py
opensearchpy/_async/client/cat.py
opensearchpy/_async/client/client.py
opensearchpy/_async/client/cluster.py
opensearchpy/_async/client/dangling_indices.py
opensearchpy/_async/client/features.py
opensearchpy/_async/client/http.py
opensearchpy/_async/client/indices.py
opensearchpy/_async/client/ingest.py
opensearchpy/_async/client/nodes.py
opensearchpy/_async/client/plugins.py
opensearchpy/_async/client/remote.py
opensearchpy/_async/client/remote_store.py
opensearchpy/_async/client/security.py
opensearchpy/_async/client/snapshot.py
opensearchpy/_async/client/tasks.py
opensearchpy/_async/client/utils.py
opensearchpy/_async/helpers/__init__.py
opensearchpy/_async/helpers/actions.py
opensearchpy/_async/helpers/document.py
opensearchpy/_async/helpers/faceted_search.py
opensearchpy/_async/helpers/index.py
opensearchpy/_async/helpers/mapping.py
opensearchpy/_async/helpers/search.py
opensearchpy/_async/helpers/test.py
opensearchpy/_async/helpers/update_by_query.py
opensearchpy/_async/plugins/__init__.py
opensearchpy/_async/plugins/alerting.py
opensearchpy/_async/plugins/index_management.py
opensearchpy/_async/plugins/knn.py
opensearchpy/client/__init__.py
opensearchpy/client/_patch.py
opensearchpy/client/cat.py
opensearchpy/client/client.py
opensearchpy/client/cluster.py
opensearchpy/client/dangling_indices.py
opensearchpy/client/features.py
opensearchpy/client/http.py
opensearchpy/client/indices.py
opensearchpy/client/ingest.py
opensearchpy/client/nodes.py
opensearchpy/client/plugins.py
opensearchpy/client/remote.py
opensearch_py-2.5.0.dist-info/AUTHORS
opensearch_py-2.5.0.dist-info/LICENSE.txt
opensearch_py-2.5.0.dist-info/METADATA
opensearch_py-2.5.0.dist-info/NOTICE.txt
opensearch_py-2.5.0.dist-info/WHEEL
opensearch_py-2.5.0.dist-info/top_level.txt
opensearch_py-2.5.0.dist-info/RECORD
